pulumi_consul/__init__.py
pulumi_consul/_inputs.py
pulumi_consul/_utilities.py
pulumi_consul/acl_auth_method.py
pulumi_consul/acl_binding_rule.py
pulumi_consul/acl_policy.py
pulumi_consul/acl_role.py
pulumi_consul/acl_role_policy_attachment.py
pulumi_consul/acl_token.py
pulumi_consul/acl_token_policy_attachment.py
pulumi_consul/acl_token_role_attachment.py
pulumi_consul/admin_partition.py
pulumi_consul/agent_service.py
pulumi_consul/autopilot_config.py
pulumi_consul/catalog_entry.py
pulumi_consul/certificate_authority.py
pulumi_consul/config_entry.py
pulumi_consul/config_entry_service_defaults.py
pulumi_consul/config_entry_service_intentions.py
pulumi_consul/config_entry_service_resolver.py
pulumi_consul/config_entry_service_router.py
pulumi_consul/config_entry_service_splitter.py
pulumi_consul/config_entry_v2_exported_services.py
pulumi_consul/get_acl_auth_method.py
pulumi_consul/get_acl_policy.py
pulumi_consul/get_acl_role.py
pulumi_consul/get_acl_token.py
pulumi_consul/get_acl_token_secret_id.py
pulumi_consul/get_agent_config.py
pulumi_consul/get_agent_self.py
pulumi_consul/get_autopilot_health.py
pulumi_consul/get_catalog_nodes.py
pulumi_consul/get_catalog_service.py
pulumi_consul/get_catalog_services.py
pulumi_consul/get_config_entry.py
pulumi_consul/get_config_entry_v2_exported_services.py
pulumi_consul/get_datacenters.py
pulumi_consul/get_key_prefix.py
pulumi_consul/get_keys.py
pulumi_consul/get_network_area_members.py
pulumi_consul/get_network_segments.py
pulumi_consul/get_nodes.py
pulumi_consul/get_peering.py
pulumi_consul/get_peerings.py
pulumi_consul/get_service.py
pulumi_consul/get_service_health.py
pulumi_consul/get_services.py
pulumi_consul/intention.py
pulumi_consul/key_prefix.py
pulumi_consul/keys.py
pulumi_consul/license.py
pulumi_consul/namespace.py
pulumi_consul/namespace_policy_attachment.py
pulumi_consul/namespace_role_attachment.py
pulumi_consul/network_area.py
pulumi_consul/node.py
pulumi_consul/outputs.py
pulumi_consul/peering.py
pulumi_consul-3.14.0.dist-info/METADATA
pulumi_consul-3.14.0.dist-info/WHEEL
pulumi_consul-3.14.0.dist-info/top_level.txt
pulumi_consul-3.14.0.dist-info/RECORD
